LICENSE
README.md
pyproject.toml
setup.cfg
setup.py
negspacy/__init__.py
negspacy/negation.py
negspacy/termsets.py
negspacy/test.py
negspacy/test_scispacy_dep.py
negspacy.egg-info/PKG-INFO
negspacy.egg-info/SOURCES.txt
negspacy.egg-info/dependency_links.txt
negspacy.egg-info/requires.txt
negspacy.egg-info/top_level.txt